assembler/__init__.py
assembler/generics/__init__.py
assembler/generics/core.py
assembler/generics/file.py
assembler/job/__init__.py
assembler/job/assemble.py
assembler/job/job.py
assembler/job/page.py
assembler/template/__init__.py
assembler/template/context.py
assembler/template/prepper.py
assembler/template/processor.py
assembler/template/tag.py
assembler/template/template.py
assembler/template/token.py
assembler/template/token_filter.py
djist-0.1.0.dist-info/LICENSE
djist-0.1.0.dist-info/METADATA
djist-0.1.0.dist-info/WHEEL
djist-0.1.0.dist-info/top_level.txt
djist-0.1.0.dist-info/RECORD
