Metadata-Version: 2.1
Name: djist
Version: 0.1.0
Summary: Django-inspired static templates
Home-page: https://github.com/llelse/djist
Author: liorelse
Author-email: buggyfirmware@protonmail.com
License: UNKNOWN
Platform: UNKNOWN
Classifier: Programming Language :: Python :: 3
Classifier: License :: OSI Approved :: GNU General Public License v3 (GPLv3)
Classifier: Operating System :: OS Independent
Classifier: Development Status :: 3 - Alpha
Requires-Python: >=3.6
